termai/__init__.py
termai/__main__.py
termai/cli.py
termai/config.py
termai/handlers.py
termai/prompts.py
termai/providers.py
termai/server.py
termai/utils.py
termai/scripts/install-shell-integration.sh
termai/scripts/uninstall-shell-integration.sh
termaitrik-1.7.2.dist-info/licenses/LICENSE
termaitrik-1.7.2.dist-info/METADATA
termaitrik-1.7.2.dist-info/WHEEL
termaitrik-1.7.2.dist-info/entry_points.txt
termaitrik-1.7.2.dist-info/top_level.txt
termaitrik-1.7.2.dist-info/RECORD
