Metadata-Version: 2.4
Name: termaitrik
Version: 1.7.2
Summary: Terminal AI assistant inspired by Warp AI, supporting Ollama and BYOK
Author: Trikketto
Maintainer: Trikketto
License-Expression: MIT
Project-URL: Homepage, https://github.com/Trikketto/termai_project
Project-URL: Repository, https://github.com/Trikketto/termai_project
Project-URL: Issues, https://github.com/Trikketto/termai_project/issues
Keywords: ai,terminal,ollama,cli,assistant
Classifier: Development Status :: 4 - Beta
Classifier: Intended Audience :: Developers
Classifier: Operating System :: OS Independent
Classifier: Programming Language :: Python :: 3
Classifier: Programming Language :: Python :: 3.10
Classifier: Programming Language :: Python :: 3.11
Classifier: Programming Language :: Python :: 3.12
Classifier: Topic :: Utilities
Requires-Python: >=3.10
License-File: LICENSE
Requires-Dist: fastapi>=0.111
Requires-Dist: uvicorn>=0.30
Requires-Dist: typer>=0.12
Requires-Dist: rich>=13.7
Requires-Dist: PyYAML>=6.0
Requires-Dist: requests>=2.31
Requires-Dist: llama-cpp-python
Dynamic: license-file
